tag_fixer/__init__.py
tag_fixer/tag_fixer.py
tag_fixer-0.0.4.dist-info/METADATA
tag_fixer-0.0.4.dist-info/WHEEL
tag_fixer-0.0.4.dist-info/top_level.txt
tag_fixer-0.0.4.dist-info/RECORD
