Metadata-Version: 2.1
Name: tag-fixer
Version: 0.0.4
Summary: A simple interface for checking and fixing POS tags
Home-page: https://github.com/kristopherkyle/tag_fixer
Author: Kristopher Kyle
Author-email: kristopherkyle1@gmail.com
License: UNKNOWN
Platform: UNKNOWN
Classifier: Programming Language :: Python :: 3
Classifier: License :: OSI Approved :: MIT License
Classifier: Operating System :: OS Independent
